{"action":{"identity":{"address":"N\u0000sourcecred\u0000core\u0000IDENTITY\u0000m5MWi1wt1pXZ1xRaoSwDWQ\u0000","aliases":[],"id":"m5MWi1wt1pXZ1xRaoSwDWQ","name":"Shael","subtype":"USER"},"type":"CREATE_IDENTITY"},"ledgerTimestamp":1643930401168,"uuid":"EvBOeK0eqJqawTvwPHN6bg","version":"1"}
{"action":{"alias":{"address":"N\u0000sourcecred\u0000discord\u0000MEMBER\u0000user\u0000110524426960818176\u0000","description":"discord/Shael#0165"},"identityId":"m5MWi1wt1pXZ1xRaoSwDWQ","type":"ADD_ALIAS"},"ledgerTimestamp":1643930401171,"uuid":"qbHy5gPvhxHXaTZXM3XfBw","version":"1"}
{"action":{"identity":{"address":"N\u0000sourcecred\u0000core\u0000IDENTITY\u0000RuNzrF1peBh0rtauMXJViQ\u0000","aliases":[],"id":"RuNzrF1peBh0rtauMXJViQ","name":"Dilworth","subtype":"USER"},"type":"CREATE_IDENTITY"},"ledgerTimestamp":1643930401172,"uuid":"ikptrCjC3KvnQlZGZnIeFg","version":"1"}
{"action":{"alias":{"address":"N\u0000sourcecred\u0000discord\u0000MEMBER\u0000user\u0000135488705153466368\u0000","description":"discord/Dilworth#2909"},"identityId":"RuNzrF1peBh0rtauMXJViQ","type":"ADD_ALIAS"},"ledgerTimestamp":1643930401172,"uuid":"CEKX8RgpFktz68eVeREoDg","version":"1"}
{"action":{"identity":{"address":"N\u0000sourcecred\u0000core\u0000IDENTITY\u0000PvI4oziDRyE7wTg3iPmQlw\u0000","aliases":[],"id":"PvI4oziDRyE7wTg3iPmQlw","name":"Whazz-aka-Jeff","subtype":"USER"},"type":"CREATE_IDENTITY"},"ledgerTimestamp":1643930401172,"uuid":"q163JAbYx8tDVKR3DCPvDQ","version":"1"}
{"action":{"alias":{"address":"N\u0000sourcecred\u0000discord\u0000MEMBER\u0000user\u0000143425464688574464\u0000","description":"discord/Whazz-aka-Jeff#4979"},"identityId":"PvI4oziDRyE7wTg3iPmQlw","type":"ADD_ALIAS"},"ledgerTimestamp":1643930401173,"uuid":"cBEjH7BYEJB7BaMy0BOMUw","version":"1"}
{"action":{"identity":{"address":"N\u0000sourcecred\u0000core\u0000IDENTITY\u0000qxaEjOQOovpwAePZGptODg\u0000","aliases":[],"id":"qxaEjOQOovpwAePZGptODg","name":"George-Lovegrove","subtype":"USER"},"type":"CREATE_IDENTITY"},"ledgerTimestamp":1643930401174,"uuid":"YYPPlXEoMMLqfPwv1kFGlw","version":"1"}
{"action":{"alias":{"address":"N\u0000sourcecred\u0000discord\u0000MEMBER\u0000user\u0000144835871525306368\u0000","description":"discord/George-Lovegrove#3020"},"identityId":"qxaEjOQOovpwAePZGptODg","type":"ADD_ALIAS"},"ledgerTimestamp":1643930401174,"uuid":"W8YyGsbSypLjYuwbSAZzQw","version":"1"}
{"action":{"identity":{"address":"N\u0000sourcecred\u0000core\u0000IDENTITY\u0000dQDtaMZ0qMnQNOK1UzXmtg\u0000","aliases":[],"id":"dQDtaMZ0qMnQNOK1UzXmtg","name":"MEE6","subtype":"BOT"},"type":"CREATE_IDENTITY"},"ledgerTimestamp":1643930401174,"uuid":"lX6yj7iJ5xIVZRpp8WkpyQ","version":"1"}
{"action":{"alias":{"address":"N\u0000sourcecred\u0000discord\u0000MEMBER\u0000bot\u0000159985870458322944\u0000","description":"discord/MEE6#4876"},"identityId":"dQDtaMZ0qMnQNOK1UzXmtg","type":"ADD_ALIAS"},"ledgerTimestamp":1643930401175,"uuid":"4Rfww6Y4tAnU7zVZTVuJTA","version":"1"}
{"action":{"identity":{"address":"N\u0000sourcecred\u0000core\u0000IDENTITY\u0000XntK89wDi7wzFY9bAT33DQ\u0000","aliases":[],"id":"XntK89wDi7wzFY9bAT33DQ","name":"Seo4u","subtype":"USER"},"type":"CREATE_IDENTITY"},"ledgerTimestamp":1643930401175,"uuid":"YW486725vwHLIoc5DfgQ8w","version":"1"}
{"action":{"alias":{"address":"N\u0000sourcecred\u0000discord\u0000MEMBER\u0000user\u0000160981697700036608\u0000","description":"discord/Seo4u#6254"},"identityId":"XntK89wDi7wzFY9bAT33DQ","type":"ADD_ALIAS"},"ledgerTimestamp":1643930401175,"uuid":"Cyw6XkFGOGk1pUmnN8zoNQ","version":"1"}
{"action":{"identity":{"address":"N\u0000sourcecred\u0000core\u0000IDENTITY\u0000OMIyQTZvTO9W1SQKW6Tzig\u0000","aliases":[],"id":"OMIyQTZvTO9W1SQKW6Tzig","name":"CH-DDERVOX","subtype":"USER"},"type":"CREATE_IDENTITY"},"ledgerTimestamp":1643930401176,"uuid":"b8B4NZNZbyE67mxH4Gzmvw","version":"1"}
{"action":{"alias":{"address":"N\u0000sourcecred\u0000discord\u0000MEMBER\u0000user\u0000166718629214289921\u0000","description":"discord/CH-DDERVOX#8627"},"identityId":"OMIyQTZvTO9W1SQKW6Tzig","type":"ADD_ALIAS"},"ledgerTimestamp":1643930401176,"uuid":"E3XBeIgDtRv18by55hmUzw","version":"1"}
{"action":{"identity":{"address":"N\u0000sourcecred\u0000core\u0000IDENTITY\u00004o9zlDbNX4E99hZy2HmnkQ\u0000","aliases":[],"id":"4o9zlDbNX4E99hZy2HmnkQ","name":"an-ugly-man","subtype":"USER"},"type":"CREATE_IDENTITY"},"ledgerTimestamp":1643930401176,"uuid":"OBumPDvjS6YboUOkqeB5OA","version":"1"}
{"action":{"alias":{"address":"N\u0000sourcecred\u0000discord\u0000MEMBER\u0000user\u0000167762014767284224\u0000","description":"discord/an-ugly-man#6192"},"identityId":"4o9zlDbNX4E99hZy2HmnkQ","type":"ADD_ALIAS"},"ledgerTimestamp":1643930401176,"uuid":"CxWD32RI25ZayFeKqFwGQQ","version":"1"}
{"action":{"identity":{"address":"N\u0000sourcecred\u0000core\u0000IDENTITY\u0000qEqTbO4WCyJpyos1c4F8ZA\u0000","aliases":[],"id":"qEqTbO4WCyJpyos1c4F8ZA","name":"Vicc---ThHddnOrdr","subtype":"USER"},"type":"CREATE_IDENTITY"},"ledgerTimestamp":1643930401177,"uuid":"yjnoJmlTOVWo4oWVaOHkHQ","version":"1"}
{"action":{"alias":{"address":"N\u0000sourcecred\u0000discord\u0000MEMBER\u0000user\u0000183473497991938048\u0000","description":"discord/Vicc---ThHddnOrdr#6777"},"identityId":"qEqTbO4WCyJpyos1c4F8ZA","type":"ADD_ALIAS"},"ledgerTimestamp":1643930401177,"uuid":"94H2qZKn2GrTVU57svTAdA","version":"1"}
{"action":{"identity":{"address":"N\u0000sourcecred\u0000core\u0000IDENTITY\u0000aAvBa6QMc4UaGne9SX8XaA\u0000","aliases":[],"id":"aAvBa6QMc4UaGne9SX8XaA","name":"J-Doe","subtype":"USER"},"type":"CREATE_IDENTITY"},"ledgerTimestamp":1643930401177,"uuid":"UnoDaBp2Oy9SK3u21mLEMg","version":"1"}
{"action":{"alias":{"address":"N\u0000sourcecred\u0000discord\u0000MEMBER\u0000user\u0000208651061433597954\u0000","description":"discord/J-Doe#9686"},"identityId":"aAvBa6QMc4UaGne9SX8XaA","type":"ADD_ALIAS"},"ledgerTimestamp":1643930401178,"uuid":"9sdNSWQuAjhkbELBwO6G1w","version":"1"}
{"action":{"identity":{"address":"N\u0000sourcecred\u0000core\u0000IDENTITY\u0000JCm51KXN6PElxPHMnmzq1w\u0000","aliases":[],"id":"JCm51KXN6PElxPHMnmzq1w","name":"Sheridan-MADAO-IO-","subtype":"USER"},"type":"CREATE_IDENTITY"},"ledgerTimestamp":1643930401178,"uuid":"KO6VmWBt7zsOxeXuzbC2NQ","version":"1"}
{"action":{"alias":{"address":"N\u0000sourcecred\u0000discord\u0000MEMBER\u0000user\u0000220313224522760192\u0000","description":"discord/Sheridan-MADAO-IO-#8966"},"identityId":"JCm51KXN6PElxPHMnmzq1w","type":"ADD_ALIAS"},"ledgerTimestamp":1643930401178,"uuid":"Rl3w5uqoirHDcERFx7vwdQ","version":"1"}
{"action":{"identity":{"address":"N\u0000sourcecred\u0000core\u0000IDENTITY\u0000c65ROLL1APVuRm36XPK0OA\u0000","aliases":[],"id":"c65ROLL1APVuRm36XPK0OA","name":"Mars-V-","subtype":"USER"},"type":"CREATE_IDENTITY"},"ledgerTimestamp":1643930401178,"uuid":"IVQXVx0hJlvkrmMgeJ7UNQ","version":"1"}
{"action":{"alias":{"address":"N\u0000sourcecred\u0000discord\u0000MEMBER\u0000user\u0000307221443228205056\u0000","description":"discord/Mars-V-#7392"},"identityId":"c65ROLL1APVuRm36XPK0OA","type":"ADD_ALIAS"},"ledgerTimestamp":1643930401179,"uuid":"jJ8skxKGlaMqFmbvSARyEQ","version":"1"}
{"action":{"identity":{"address":"N\u0000sourcecred\u0000core\u0000IDENTITY\u00009HosOcZFewN4dy3borhLtw\u0000","aliases":[],"id":"9HosOcZFewN4dy3borhLtw","name":"PureRelativity","subtype":"USER"},"type":"CREATE_IDENTITY"},"ledgerTimestamp":1643930401179,"uuid":"KPvdkpfbD1VJiygm2L74UA","version":"1"}
{"action":{"alias":{"address":"N\u0000sourcecred\u0000discord\u0000MEMBER\u0000user\u0000316767687688585216\u0000","description":"discord/PureRelativity#3502"},"identityId":"9HosOcZFewN4dy3borhLtw","type":"ADD_ALIAS"},"ledgerTimestamp":1643930401179,"uuid":"FQveyh1vFEOKHqY2EGLwbQ","version":"1"}
{"action":{"identity":{"address":"N\u0000sourcecred\u0000core\u0000IDENTITY\u0000L1J3TesqwFRimN2rGBc63w\u0000","aliases":[],"id":"L1J3TesqwFRimN2rGBc63w","name":"DanMercurius","subtype":"USER"},"type":"CREATE_IDENTITY"},"ledgerTimestamp":1643930401180,"uuid":"8DqHVHGnvDj5GIBRXGkWwQ","version":"1"}
{"action":{"alias":{"address":"N\u0000sourcecred\u0000discord\u0000MEMBER\u0000user\u0000331572987092533248\u0000","description":"discord/DanMercurius#7990"},"identityId":"L1J3TesqwFRimN2rGBc63w","type":"ADD_ALIAS"},"ledgerTimestamp":1643930401180,"uuid":"nXbWR3MnY9ohv9CaZKsjQg","version":"1"}
{"action":{"identity":{"address":"N\u0000sourcecred\u0000core\u0000IDENTITY\u00002l8xs7KdZoW9i99WDznWAA\u0000","aliases":[],"id":"2l8xs7KdZoW9i99WDznWAA","name":"rcmorano--PEACE-","subtype":"USER"},"type":"CREATE_IDENTITY"},"ledgerTimestamp":1643930401181,"uuid":"hLtp547tBzPdQR4LwqL5Kg","version":"1"}
{"action":{"alias":{"address":"N\u0000sourcecred\u0000discord\u0000MEMBER\u0000user\u0000332306649895272450\u0000","description":"discord/rcmorano--PEACE-#7121"},"identityId":"2l8xs7KdZoW9i99WDznWAA","type":"ADD_ALIAS"},"ledgerTimestamp":1643930401181,"uuid":"aYyBgPVLcvpU1Qpf0AAdzQ","version":"1"}
{"action":{"identity":{"address":"N\u0000sourcecred\u0000core\u0000IDENTITY\u0000xbrQEWwbL0LVd0gyddG27w\u0000","aliases":[],"id":"xbrQEWwbL0LVd0gyddG27w","name":"Quasar","subtype":"USER"},"type":"CREATE_IDENTITY"},"ledgerTimestamp":1643930401181,"uuid":"6dXiX8Res5P5B3wQlDDx2A","version":"1"}
{"action":{"alias":{"address":"N\u0000sourcecred\u0000discord\u0000MEMBER\u0000user\u0000346305486829780993\u0000","description":"discord/Quasar#0436"},"identityId":"xbrQEWwbL0LVd0gyddG27w","type":"ADD_ALIAS"},"ledgerTimestamp":1643930401181,"uuid":"ehM6PC1G8BofJPrkrx2wrA","version":"1"}
{"action":{"identity":{"address":"N\u0000sourcecred\u0000core\u0000IDENTITY\u0000xFYy9ZY7eceyardYZBbt9Q\u0000","aliases":[],"id":"xFYy9ZY7eceyardYZBbt9Q","name":"Sic---","subtype":"USER"},"type":"CREATE_IDENTITY"},"ledgerTimestamp":1643930401181,"uuid":"CV3owO7dBj2Kr8qGIr7HKQ","version":"1"}
{"action":{"alias":{"address":"N\u0000sourcecred\u0000discord\u0000MEMBER\u0000user\u0000346682598107512832\u0000","description":"discord/Sic---#2336"},"identityId":"xFYy9ZY7eceyardYZBbt9Q","type":"ADD_ALIAS"},"ledgerTimestamp":1643930401182,"uuid":"OObtWhByjywIDajBLzolWg","version":"1"}
{"action":{"identity":{"address":"N\u0000sourcecred\u0000core\u0000IDENTITY\u0000vSQbFKvX75X7YJ32A3b83g\u0000","aliases":[],"id":"vSQbFKvX75X7YJ32A3b83g","name":"cloudy","subtype":"USER"},"type":"CREATE_IDENTITY"},"ledgerTimestamp":1643930401182,"uuid":"uQZujTKqPeds79oxCRnKhg","version":"1"}
{"action":{"alias":{"address":"N\u0000sourcecred\u0000discord\u0000MEMBER\u0000user\u0000354457709296353282\u0000","description":"discord/cloudy#2379"},"identityId":"vSQbFKvX75X7YJ32A3b83g","type":"ADD_ALIAS"},"ledgerTimestamp":1643930401183,"uuid":"oLm5U2atzByLrP9WAYh2LA","version":"1"}
{"action":{"identity":{"address":"N\u0000sourcecred\u0000core\u0000IDENTITY\u0000YjBwyl5XmXAp1GcMJdexeQ\u0000","aliases":[],"id":"YjBwyl5XmXAp1GcMJdexeQ","name":"iamkhayyam","subtype":"USER"},"type":"CREATE_IDENTITY"},"ledgerTimestamp":1643930401183,"uuid":"CyEIzlmM9DLInEE5U7JhlA","version":"1"}
{"action":{"alias":{"address":"N\u0000sourcecred\u0000discord\u0000MEMBER\u0000user\u0000365666435659464707\u0000","description":"discord/iamkhayyam#0001"},"identityId":"YjBwyl5XmXAp1GcMJdexeQ","type":"ADD_ALIAS"},"ledgerTimestamp":1643930401183,"uuid":"rMzmncNimPgZTDDIrl27zQ","version":"1"}
{"action":{"identity":{"address":"N\u0000sourcecred\u0000core\u0000IDENTITY\u0000rZOtepLrNcN09dxraFLKTg\u0000","aliases":[],"id":"rZOtepLrNcN09dxraFLKTg","name":"Allusian","subtype":"USER"},"type":"CREATE_IDENTITY"},"ledgerTimestamp":1643930401184,"uuid":"0B09z3mvJno3DbT16ezxyg","version":"1"}
{"action":{"alias":{"address":"N\u0000sourcecred\u0000discord\u0000MEMBER\u0000user\u0000378296345372655618\u0000","description":"discord/Allusian#7777"},"identityId":"rZOtepLrNcN09dxraFLKTg","type":"ADD_ALIAS"},"ledgerTimestamp":1643930401184,"uuid":"xkbk4AAHewu0Lq8P540zHQ","version":"1"}
{"action":{"identity":{"address":"N\u0000sourcecred\u0000core\u0000IDENTITY\u0000VHJfxl82oFyQrjOpRyOAKg\u0000","aliases":[],"id":"VHJfxl82oFyQrjOpRyOAKg","name":"Lovecoach","subtype":"USER"},"type":"CREATE_IDENTITY"},"ledgerTimestamp":1643930401184,"uuid":"amqli7d7I5k7zYazIL4AxA","version":"1"}
{"action":{"alias":{"address":"N\u0000sourcecred\u0000discord\u0000MEMBER\u0000user\u0000398868728818827274\u0000","description":"discord/Lovecoach#0556"},"identityId":"VHJfxl82oFyQrjOpRyOAKg","type":"ADD_ALIAS"},"ledgerTimestamp":1643930401185,"uuid":"Xq3mV3mbQrMR9vfwMNydOQ","version":"1"}
{"action":{"identity":{"address":"N\u0000sourcecred\u0000core\u0000IDENTITY\u0000pg8L2BwZDHzJ7WP08vvATg\u0000","aliases":[],"id":"pg8L2BwZDHzJ7WP08vvATg","name":"discord-408939488241385472","subtype":"USER"},"type":"CREATE_IDENTITY"},"ledgerTimestamp":1643930401185,"uuid":"YZn5pdQ7ORemsqMHV6K56Q","version":"1"}
{"action":{"alias":{"address":"N\u0000sourcecred\u0000discord\u0000MEMBER\u0000user\u0000408939488241385472\u0000","description":"discord/discord-408939488241385472#1802"},"identityId":"pg8L2BwZDHzJ7WP08vvATg","type":"ADD_ALIAS"},"ledgerTimestamp":1643930401185,"uuid":"TKkgHYzCWFZNkIzXM91wiw","version":"1"}
{"action":{"identity":{"address":"N\u0000sourcecred\u0000core\u0000IDENTITY\u00009KDdR7SvYiOhX6BAiKfPkA\u0000","aliases":[],"id":"9KDdR7SvYiOhX6BAiKfPkA","name":"Arcane","subtype":"BOT"},"type":"CREATE_IDENTITY"},"ledgerTimestamp":1643930401185,"uuid":"K292M2AbLAnMYeO0mC1JYQ","version":"1"}
{"action":{"alias":{"address":"N\u0000sourcecred\u0000discord\u0000MEMBER\u0000bot\u0000437808476106784770\u0000","description":"discord/Arcane#7800"},"identityId":"9KDdR7SvYiOhX6BAiKfPkA","type":"ADD_ALIAS"},"ledgerTimestamp":1643930401186,"uuid":"UGf4ki1rr23I2gL8F9M4Jg","version":"1"}
{"action":{"identity":{"address":"N\u0000sourcecred\u0000core\u0000IDENTITY\u0000Z27SvmRZ75w1nZYOFz0DaA\u0000","aliases":[],"id":"Z27SvmRZ75w1nZYOFz0DaA","name":"Pollmaster","subtype":"BOT"},"type":"CREATE_IDENTITY"},"ledgerTimestamp":1643930401186,"uuid":"cENkVpBDBEQlj51KodZvGw","version":"1"}
{"action":{"alias":{"address":"N\u0000sourcecred\u0000discord\u0000MEMBER\u0000bot\u0000444514223075360800\u0000","description":"discord/Pollmaster#1837"},"identityId":"Z27SvmRZ75w1nZYOFz0DaA","type":"ADD_ALIAS"},"ledgerTimestamp":1643930401186,"uuid":"LOZNP66oSkr9zgQjXMs7YA","version":"1"}
{"action":{"identity":{"address":"N\u0000sourcecred\u0000core\u0000IDENTITY\u00006hdjGQS9TYKHOXhqap1JOQ\u0000","aliases":[],"id":"6hdjGQS9TYKHOXhqap1JOQ","name":"timeyyy","subtype":"USER"},"type":"CREATE_IDENTITY"},"ledgerTimestamp":1643930401186,"uuid":"8bbTytNJN3BGAGMTP1qOVw","version":"1"}
{"action":{"alias":{"address":"N\u0000sourcecred\u0000discord\u0000MEMBER\u0000user\u0000460061936625909770\u0000","description":"discord/timeyyy#1502"},"identityId":"6hdjGQS9TYKHOXhqap1JOQ","type":"ADD_ALIAS"},"ledgerTimestamp":1643930401187,"uuid":"gAofV9fweOsAXJIjS3ZHMg","version":"1"}
{"action":{"identity":{"address":"N\u0000sourcecred\u0000core\u0000IDENTITY\u0000ny4GnnYQsoTl4hz4pWjubw\u0000","aliases":[],"id":"ny4GnnYQsoTl4hz4pWjubw","name":"jadjei","subtype":"USER"},"type":"CREATE_IDENTITY"},"ledgerTimestamp":1643930401187,"uuid":"xz9wgIaJcMm5rwKfKgsRRQ","version":"1"}
{"action":{"alias":{"address":"N\u0000sourcecred\u0000discord\u0000MEMBER\u0000user\u0000594691110568198154\u0000","description":"discord/jadjei#4938"},"identityId":"ny4GnnYQsoTl4hz4pWjubw","type":"ADD_ALIAS"},"ledgerTimestamp":1643930401187,"uuid":"F45GPoH5EXpoYBtqkM39qg","version":"1"}
{"action":{"identity":{"address":"N\u0000sourcecred\u0000core\u0000IDENTITY\u0000d1GgXJl9FoYf511OMPRQOw\u0000","aliases":[],"id":"d1GgXJl9FoYf511OMPRQOw","name":"sesh","subtype":"BOT"},"type":"CREATE_IDENTITY"},"ledgerTimestamp":1643930401189,"uuid":"SAenGJZOIkI78exlHOrLpw","version":"1"}
{"action":{"alias":{"address":"N\u0000sourcecred\u0000discord\u0000MEMBER\u0000bot\u0000616754792965865495\u0000","description":"discord/sesh#1244"},"identityId":"d1GgXJl9FoYf511OMPRQOw","type":"ADD_ALIAS"},"ledgerTimestamp":1643930401189,"uuid":"hoHdF1PvKpoNwANkYOfrlA","version":"1"}
{"action":{"identity":{"address":"N\u0000sourcecred\u0000core\u0000IDENTITY\u0000a4DdF17XPc8tkd8X0zg6EA\u0000","aliases":[],"id":"a4DdF17XPc8tkd8X0zg6EA","name":"Jonathan-pxlz","subtype":"USER"},"type":"CREATE_IDENTITY"},"ledgerTimestamp":1643930401190,"uuid":"W18hn5mJdcZFD2LmS7bqRg","version":"1"}
{"action":{"alias":{"address":"N\u0000sourcecred\u0000discord\u0000MEMBER\u0000user\u0000621385648779296781\u0000","description":"discord/Jonathan-pxlz#7521"},"identityId":"a4DdF17XPc8tkd8X0zg6EA","type":"ADD_ALIAS"},"ledgerTimestamp":1643930401190,"uuid":"mTmN98KZgeKL6ja9fKo1gQ","version":"1"}
{"action":{"identity":{"address":"N\u0000sourcecred\u0000core\u0000IDENTITY\u0000s2GVaA9kMqagp1ldSjkayw\u0000","aliases":[],"id":"s2GVaA9kMqagp1ldSjkayw","name":"Eddie-Chu","subtype":"USER"},"type":"CREATE_IDENTITY"},"ledgerTimestamp":1643930401190,"uuid":"lCdXNWW7DEgaEMoFvwwzCQ","version":"1"}
{"action":{"alias":{"address":"N\u0000sourcecred\u0000discord\u0000MEMBER\u0000user\u0000669702048186499121\u0000","description":"discord/Eddie-Chu#2705"},"identityId":"s2GVaA9kMqagp1ldSjkayw","type":"ADD_ALIAS"},"ledgerTimestamp":1643930401190,"uuid":"qswXRx63EBI7EQCXKRn6WQ","version":"1"}
{"action":{"identity":{"address":"N\u0000sourcecred\u0000core\u0000IDENTITY\u000036SYmVcWbNL66xj2qmUA6w\u0000","aliases":[],"id":"36SYmVcWbNL66xj2qmUA6w","name":"Gnoman","subtype":"USER"},"type":"CREATE_IDENTITY"},"ledgerTimestamp":1643930401190,"uuid":"GNsJeAJP4JHw17EsNpR7Bw","version":"1"}
{"action":{"alias":{"address":"N\u0000sourcecred\u0000discord\u0000MEMBER\u0000user\u0000680524422221791249\u0000","description":"discord/Gnoman#3176"},"identityId":"36SYmVcWbNL66xj2qmUA6w","type":"ADD_ALIAS"},"ledgerTimestamp":1643930401190,"uuid":"WZGwDG1IL7z5s7XRqbiLrw","version":"1"}
{"action":{"identity":{"address":"N\u0000sourcecred\u0000core\u0000IDENTITY\u0000YVq0Rzv6o6Vj48NHJzCo3Q\u0000","aliases":[],"id":"YVq0Rzv6o6Vj48NHJzCo3Q","name":"severoni","subtype":"USER"},"type":"CREATE_IDENTITY"},"ledgerTimestamp":1643930401190,"uuid":"JML9WtZHn70F4QyEbXHB7w","version":"1"}
{"action":{"alias":{"address":"N\u0000sourcecred\u0000discord\u0000MEMBER\u0000user\u0000690493428860977182\u0000","description":"discord/severoni#1573"},"identityId":"YVq0Rzv6o6Vj48NHJzCo3Q","type":"ADD_ALIAS"},"ledgerTimestamp":1643930401190,"uuid":"niYkrOx8y8uo7Z4SXlvNtA","version":"1"}
{"action":{"identity":{"address":"N\u0000sourcecred\u0000core\u0000IDENTITY\u0000b21pHoOVYjw3u2A7AkZYHA\u0000","aliases":[],"id":"b21pHoOVYjw3u2A7AkZYHA","name":"Heather","subtype":"USER"},"type":"CREATE_IDENTITY"},"ledgerTimestamp":1643930401191,"uuid":"1d6RBad0gpNnPavzUjQe7w","version":"1"}
{"action":{"alias":{"address":"N\u0000sourcecred\u0000discord\u0000MEMBER\u0000user\u0000691019186444566631\u0000","description":"discord/Heather#2399"},"identityId":"b21pHoOVYjw3u2A7AkZYHA","type":"ADD_ALIAS"},"ledgerTimestamp":1643930401191,"uuid":"rX6nSAI17FQb4UDYROUgGg","version":"1"}
{"action":{"identity":{"address":"N\u0000sourcecred\u0000core\u0000IDENTITY\u0000eqTjSZESQjG2Da9EcG0Fdg\u0000","aliases":[],"id":"eqTjSZESQjG2Da9EcG0Fdg","name":"Methiseus","subtype":"USER"},"type":"CREATE_IDENTITY"},"ledgerTimestamp":1643930401191,"uuid":"RzkTkgVNwwVhKJZlDfoEAg","version":"1"}
{"action":{"alias":{"address":"N\u0000sourcecred\u0000discord\u0000MEMBER\u0000user\u0000711843878021627925\u0000","description":"discord/Methiseus#9499"},"identityId":"eqTjSZESQjG2Da9EcG0Fdg","type":"ADD_ALIAS"},"ledgerTimestamp":1643930401192,"uuid":"yVRTXPgVfdeC0zXs4qZ7Tg","version":"1"}
{"action":{"identity":{"address":"N\u0000sourcecred\u0000core\u0000IDENTITY\u00008BG5XzjL8VX7OGuYNUoQwg\u0000","aliases":[],"id":"8BG5XzjL8VX7OGuYNUoQwg","name":"tyler-w","subtype":"USER"},"type":"CREATE_IDENTITY"},"ledgerTimestamp":1643930401192,"uuid":"cJkPVBSaBhKw6vohoW6drA","version":"1"}
{"action":{"alias":{"address":"N\u0000sourcecred\u0000discord\u0000MEMBER\u0000user\u0000713105321622634588\u0000","description":"discord/tyler-w#0730"},"identityId":"8BG5XzjL8VX7OGuYNUoQwg","type":"ADD_ALIAS"},"ledgerTimestamp":1643930401192,"uuid":"zz6U1V1p3cpTq6lA67YtOw","version":"1"}
{"action":{"identity":{"address":"N\u0000sourcecred\u0000core\u0000IDENTITY\u0000eUPyL6BwJlAymVHglHKkvA\u0000","aliases":[],"id":"eUPyL6BwJlAymVHglHKkvA","name":"Randall","subtype":"USER"},"type":"CREATE_IDENTITY"},"ledgerTimestamp":1643930401193,"uuid":"VrUWCNeQAmZUem0e2Kfj6w","version":"1"}
{"action":{"alias":{"address":"N\u0000sourcecred\u0000discord\u0000MEMBER\u0000user\u0000720703131104575539\u0000","description":"discord/Randall#1815"},"identityId":"eUPyL6BwJlAymVHglHKkvA","type":"ADD_ALIAS"},"ledgerTimestamp":1643930401193,"uuid":"w2h7OAvt6cB2Mgnd3AlI4w","version":"1"}
{"action":{"identity":{"address":"N\u0000sourcecred\u0000core\u0000IDENTITY\u0000YB08euzj2G5jKD09bjsOow\u0000","aliases":[],"id":"YB08euzj2G5jKD09bjsOow","name":"Pythagorean","subtype":"USER"},"type":"CREATE_IDENTITY"},"ledgerTimestamp":1643930401193,"uuid":"9R323bG996QK4iQzI7e5Fw","version":"1"}
{"action":{"alias":{"address":"N\u0000sourcecred\u0000discord\u0000MEMBER\u0000user\u0000722925809916182558\u0000","description":"discord/Pythagorean#5361"},"identityId":"YB08euzj2G5jKD09bjsOow","type":"ADD_ALIAS"},"ledgerTimestamp":1643930401194,"uuid":"GYLvwngU6BwbhPwr0K1Ofw","version":"1"}
{"action":{"identity":{"address":"N\u0000sourcecred\u0000core\u0000IDENTITY\u0000r1mgiRGWMkABDoWf8eBVBA\u0000","aliases":[],"id":"r1mgiRGWMkABDoWf8eBVBA","name":"Kathi","subtype":"USER"},"type":"CREATE_IDENTITY"},"ledgerTimestamp":1643930401194,"uuid":"56girG7IoDdZ4SA9jLoYiA","version":"1"}
{"action":{"alias":{"address":"N\u0000sourcecred\u0000discord\u0000MEMBER\u0000user\u0000758496407148691467\u0000","description":"discord/Kathi#6781"},"identityId":"r1mgiRGWMkABDoWf8eBVBA","type":"ADD_ALIAS"},"ledgerTimestamp":1643930401194,"uuid":"N5cloRmk6B7as2863k448Q","version":"1"}
{"action":{"identity":{"address":"N\u0000sourcecred\u0000core\u0000IDENTITY\u0000Ox2iMz9LiyNmZ0HMXa20Fw\u0000","aliases":[],"id":"Ox2iMz9LiyNmZ0HMXa20Fw","name":"Cipher","subtype":"USER"},"type":"CREATE_IDENTITY"},"ledgerTimestamp":1643930401195,"uuid":"xFO8fnQ4Fxk6eaxNghk38g","version":"1"}
{"action":{"alias":{"address":"N\u0000sourcecred\u0000discord\u0000MEMBER\u0000user\u0000762750423462576128\u0000","description":"discord/Cipher#8288"},"identityId":"Ox2iMz9LiyNmZ0HMXa20Fw","type":"ADD_ALIAS"},"ledgerTimestamp":1643930401196,"uuid":"3VcOcOPdwbJN958IAzfbXg","version":"1"}
{"action":{"identity":{"address":"N\u0000sourcecred\u0000core\u0000IDENTITY\u0000IQPEX66oG6S4uWHmzugtGA\u0000","aliases":[],"id":"IQPEX66oG6S4uWHmzugtGA","name":"DAG1","subtype":"USER"},"type":"CREATE_IDENTITY"},"ledgerTimestamp":1643930401196,"uuid":"dbaou9ro3YMJEjJvvCeFKw","version":"1"}
{"action":{"alias":{"address":"N\u0000sourcecred\u0000discord\u0000MEMBER\u0000user\u0000775041882824376390\u0000","description":"discord/DAG1#9091"},"identityId":"IQPEX66oG6S4uWHmzugtGA","type":"ADD_ALIAS"},"ledgerTimestamp":1643930401197,"uuid":"vHRL4Qb6WGyOiE63w1F7cg","version":"1"}
{"action":{"identity":{"address":"N\u0000sourcecred\u0000core\u0000IDENTITY\u0000OnUpcvI2u4g0wNcy1yrWDA\u0000","aliases":[],"id":"OnUpcvI2u4g0wNcy1yrWDA","name":"Garance","subtype":"USER"},"type":"CREATE_IDENTITY"},"ledgerTimestamp":1643930401197,"uuid":"3wHapVGw6x0NlqIvyxdcMw","version":"1"}
{"action":{"alias":{"address":"N\u0000sourcecred\u0000discord\u0000MEMBER\u0000user\u0000775290526429741056\u0000","description":"discord/Garance#1932"},"identityId":"OnUpcvI2u4g0wNcy1yrWDA","type":"ADD_ALIAS"},"ledgerTimestamp":1643930401197,"uuid":"1t4crdV5v50zVELlTPpw9Q","version":"1"}
{"action":{"identity":{"address":"N\u0000sourcecred\u0000core\u0000IDENTITY\u0000LAN6ONvFrxjXbaP017E2zA\u0000","aliases":[],"id":"LAN6ONvFrxjXbaP017E2zA","name":"Steve-Lockhart","subtype":"USER"},"type":"CREATE_IDENTITY"},"ledgerTimestamp":1643930401197,"uuid":"qqYvHE389CNaWK96N7qfMw","version":"1"}
{"action":{"alias":{"address":"N\u0000sourcecred\u0000discord\u0000MEMBER\u0000user\u0000787747120094117949\u0000","description":"discord/Steve-Lockhart#5327"},"identityId":"LAN6ONvFrxjXbaP017E2zA","type":"ADD_ALIAS"},"ledgerTimestamp":1643930401198,"uuid":"Y2AAXRoAQi8Dp4muJvwycQ","version":"1"}
{"action":{"identity":{"address":"N\u0000sourcecred\u0000core\u0000IDENTITY\u0000QcOOPmcP9GxC9etkxs7zmg\u0000","aliases":[],"id":"QcOOPmcP9GxC9etkxs7zmg","name":"Eva--GINGR-","subtype":"USER"},"type":"CREATE_IDENTITY"},"ledgerTimestamp":1643930401198,"uuid":"PxysPpuq0H1Qrh7yS4y40g","version":"1"}
{"action":{"alias":{"address":"N\u0000sourcecred\u0000discord\u0000MEMBER\u0000user\u0000791989121983053824\u0000","description":"discord/Eva--GINGR-#7609"},"identityId":"QcOOPmcP9GxC9etkxs7zmg","type":"ADD_ALIAS"},"ledgerTimestamp":1643930401198,"uuid":"ivubNbiD0WW3DjmbQYmCyw","version":"1"}
{"action":{"identity":{"address":"N\u0000sourcecred\u0000core\u0000IDENTITY\u00007NPvJqAuzpdeGAT5Oikv7g\u0000","aliases":[],"id":"7NPvJqAuzpdeGAT5Oikv7g","name":"troy","subtype":"USER"},"type":"CREATE_IDENTITY"},"ledgerTimestamp":1643930401199,"uuid":"1NQc24iE0uPepAoJiX66jQ","version":"1"}
{"action":{"alias":{"address":"N\u0000sourcecred\u0000discord\u0000MEMBER\u0000user\u0000801532788737310740\u0000","description":"discord/troy#4865"},"identityId":"7NPvJqAuzpdeGAT5Oikv7g","type":"ADD_ALIAS"},"ledgerTimestamp":1643930401199,"uuid":"fx1eswGLTRv2JRI7DdolJA","version":"1"}
{"action":{"identity":{"address":"N\u0000sourcecred\u0000core\u0000IDENTITY\u00000M4h76CNkYmYoebqOECzKA\u0000","aliases":[],"id":"0M4h76CNkYmYoebqOECzKA","name":"PollBotPlus","subtype":"BOT"},"type":"CREATE_IDENTITY"},"ledgerTimestamp":1643930401199,"uuid":"MLimBYE7BgfVgWRNILvXzg","version":"1"}
{"action":{"alias":{"address":"N\u0000sourcecred\u0000discord\u0000MEMBER\u0000bot\u0000804245390642642965\u0000","description":"discord/PollBotPlus#8533"},"identityId":"0M4h76CNkYmYoebqOECzKA","type":"ADD_ALIAS"},"ledgerTimestamp":1643930401200,"uuid":"S620l8b5x43DkrU5zpdLWg","version":"1"}
{"action":{"identity":{"address":"N\u0000sourcecred\u0000core\u0000IDENTITY\u0000gwoSbUMtODmNVGVjgOTZAQ\u0000","aliases":[],"id":"gwoSbUMtODmNVGVjgOTZAQ","name":"JO8N","subtype":"USER"},"type":"CREATE_IDENTITY"},"ledgerTimestamp":1643930401200,"uuid":"9K2Fasq0BVHKzkw7BWtA6w","version":"1"}
{"action":{"alias":{"address":"N\u0000sourcecred\u0000discord\u0000MEMBER\u0000user\u0000806090872596332554\u0000","description":"discord/JO8N#0850"},"identityId":"gwoSbUMtODmNVGVjgOTZAQ","type":"ADD_ALIAS"},"ledgerTimestamp":1643930401200,"uuid":"elPmVQOJ4Ls3kVTkN3nLLg","version":"1"}
{"action":{"identity":{"address":"N\u0000sourcecred\u0000core\u0000IDENTITY\u0000zdLvgYXK5irZqryTnke0zA\u0000","aliases":[],"id":"zdLvgYXK5irZqryTnke0zA","name":"Vashftw-gg","subtype":"USER"},"type":"CREATE_IDENTITY"},"ledgerTimestamp":1643930401200,"uuid":"KtzMjEA1DlmL4AAmdNImaw","version":"1"}
{"action":{"alias":{"address":"N\u0000sourcecred\u0000discord\u0000MEMBER\u0000user\u0000812293056694321172\u0000","description":"discord/Vashftw-gg#2932"},"identityId":"zdLvgYXK5irZqryTnke0zA","type":"ADD_ALIAS"},"ledgerTimestamp":1643930401201,"uuid":"4iDAKTeRtn4lVMwKALqyiQ","version":"1"}
{"action":{"identity":{"address":"N\u0000sourcecred\u0000core\u0000IDENTITY\u0000WMEhMg3Um6XwVKeDx9ygvw\u0000","aliases":[],"id":"WMEhMg3Um6XwVKeDx9ygvw","name":"Stephen--SWARM--QADAO-","subtype":"USER"},"type":"CREATE_IDENTITY"},"ledgerTimestamp":1643930401201,"uuid":"68XQx9dBrVoGigGkXS4Uaw","version":"1"}
{"action":{"alias":{"address":"N\u0000sourcecred\u0000discord\u0000MEMBER\u0000user\u0000815334780391915592\u0000","description":"discord/Stephen--SWARM--QADAO-#7396"},"identityId":"WMEhMg3Um6XwVKeDx9ygvw","type":"ADD_ALIAS"},"ledgerTimestamp":1643930401201,"uuid":"YeuBjo924rNpgFws2Iay5Q","version":"1"}
{"action":{"identity":{"address":"N\u0000sourcecred\u0000core\u0000IDENTITY\u0000FdwvLt65crgkk1AC09zbvw\u0000","aliases":[],"id":"FdwvLt65crgkk1AC09zbvw","name":"Felix--SWARM-","subtype":"USER"},"type":"CREATE_IDENTITY"},"ledgerTimestamp":1643930401202,"uuid":"dJ2QSXhoGHyrKguJZRZXfQ","version":"1"}
{"action":{"alias":{"address":"N\u0000sourcecred\u0000discord\u0000MEMBER\u0000user\u0000820728090778533928\u0000","description":"discord/Felix--SWARM-#9839"},"identityId":"FdwvLt65crgkk1AC09zbvw","type":"ADD_ALIAS"},"ledgerTimestamp":1643930401202,"uuid":"XaKJTeNlBrZ7cJNhNig0LA","version":"1"}
{"action":{"identity":{"address":"N\u0000sourcecred\u0000core\u0000IDENTITY\u0000rO0jBP4Z8G98XXdgcbQFdg\u0000","aliases":[],"id":"rO0jBP4Z8G98XXdgcbQFdg","name":"LucasCounter","subtype":"USER"},"type":"CREATE_IDENTITY"},"ledgerTimestamp":1643930401202,"uuid":"x8v0PAp8wl2jBNim7j57VQ","version":"1"}
{"action":{"alias":{"address":"N\u0000sourcecred\u0000discord\u0000MEMBER\u0000user\u0000820741075308118036\u0000","description":"discord/LucasCounter#8780"},"identityId":"rO0jBP4Z8G98XXdgcbQFdg","type":"ADD_ALIAS"},"ledgerTimestamp":1643930401202,"uuid":"CRT2vWSG8pKl8eGkwWQJAA","version":"1"}
{"action":{"identity":{"address":"N\u0000sourcecred\u0000core\u0000IDENTITY\u0000gjwYGkjdgMCD7iP2uOt6dw\u0000","aliases":[],"id":"gjwYGkjdgMCD7iP2uOt6dw","name":"Marionbierling","subtype":"USER"},"type":"CREATE_IDENTITY"},"ledgerTimestamp":1643930401202,"uuid":"bOJx93eC1T9DuMS7P9jNTg","version":"1"}
{"action":{"alias":{"address":"N\u0000sourcecred\u0000discord\u0000MEMBER\u0000user\u0000821310193991417896\u0000","description":"discord/Marionbierling#3518"},"identityId":"gjwYGkjdgMCD7iP2uOt6dw","type":"ADD_ALIAS"},"ledgerTimestamp":1643930401203,"uuid":"p7gTrK6ipZfwbzBFovljoQ","version":"1"}
{"action":{"identity":{"address":"N\u0000sourcecred\u0000core\u0000IDENTITY\u0000lMiMnkMrYE7yds0KIwVWXA\u0000","aliases":[],"id":"lMiMnkMrYE7yds0KIwVWXA","name":"kato","subtype":"USER"},"type":"CREATE_IDENTITY"},"ledgerTimestamp":1643930401203,"uuid":"cNmY0cwkHW6fRQ15IaGjMw","version":"1"}
{"action":{"alias":{"address":"N\u0000sourcecred\u0000discord\u0000MEMBER\u0000user\u0000825001815082926141\u0000","description":"discord/kato#2047"},"identityId":"lMiMnkMrYE7yds0KIwVWXA","type":"ADD_ALIAS"},"ledgerTimestamp":1643930401203,"uuid":"lHwQE7xgbBMxJsboZughkQ","version":"1"}
{"action":{"identity":{"address":"N\u0000sourcecred\u0000core\u0000IDENTITY\u00006D3nNf4XrkhlCEIVpdyiXw\u0000","aliases":[],"id":"6D3nNf4XrkhlCEIVpdyiXw","name":"Cryptonian1234","subtype":"USER"},"type":"CREATE_IDENTITY"},"ledgerTimestamp":1643930401203,"uuid":"0JIPPXSnpPyYrDOahbXi1Q","version":"1"}
{"action":{"alias":{"address":"N\u0000sourcecred\u0000discord\u0000MEMBER\u0000user\u0000828610143427624991\u0000","description":"discord/Cryptonian1234#7257"},"identityId":"6D3nNf4XrkhlCEIVpdyiXw","type":"ADD_ALIAS"},"ledgerTimestamp":1643930401203,"uuid":"778aECLKKyqjllQv0JCkIg","version":"1"}
{"action":{"identity":{"address":"N\u0000sourcecred\u0000core\u0000IDENTITY\u00007wxlDIQMI9Y9mixWbgHNKw\u0000","aliases":[],"id":"7wxlDIQMI9Y9mixWbgHNKw","name":"ryanultralifeio","subtype":"USER"},"type":"CREATE_IDENTITY"},"ledgerTimestamp":1643930401204,"uuid":"VqHPOFy4dpoUY9Ho8GDQaA","version":"1"}
{"action":{"alias":{"address":"N\u0000sourcecred\u0000discord\u0000MEMBER\u0000user\u0000830949745727373312\u0000","description":"discord/ryanultralifeio#6865"},"identityId":"7wxlDIQMI9Y9mixWbgHNKw","type":"ADD_ALIAS"},"ledgerTimestamp":1643930401205,"uuid":"oOGvtVxf48YFXbhGyhDyfg","version":"1"}
{"action":{"identity":{"address":"N\u0000sourcecred\u0000core\u0000IDENTITY\u0000BOh0ZZ4lKotLSdrdn2zeaA\u0000","aliases":[],"id":"BOh0ZZ4lKotLSdrdn2zeaA","name":"cmplx","subtype":"USER"},"type":"CREATE_IDENTITY"},"ledgerTimestamp":1643930401205,"uuid":"aBoEJ1XXPzvzspwDdTwZgA","version":"1"}
{"action":{"alias":{"address":"N\u0000sourcecred\u0000discord\u0000MEMBER\u0000user\u0000842008222458183700\u0000","description":"discord/cmplx#7297"},"identityId":"BOh0ZZ4lKotLSdrdn2zeaA","type":"ADD_ALIAS"},"ledgerTimestamp":1643930401205,"uuid":"JNN2J4jYGPxMrR8ruw2jbQ","version":"1"}
{"action":{"identity":{"address":"N\u0000sourcecred\u0000core\u0000IDENTITY\u0000C22dn5sBAaF6DEVc714vig\u0000","aliases":[],"id":"C22dn5sBAaF6DEVc714vig","name":"cmplx-discord","subtype":"USER"},"type":"CREATE_IDENTITY"},"ledgerTimestamp":1643930401205,"uuid":"G9cpAoeeV4xBxSpCgTQ8kQ","version":"1"}
{"action":{"alias":{"address":"N\u0000sourcecred\u0000discord\u0000MEMBER\u0000user\u0000842010320540008460\u0000","description":"discord/cmplx#5348"},"identityId":"C22dn5sBAaF6DEVc714vig","type":"ADD_ALIAS"},"ledgerTimestamp":1643930401205,"uuid":"h9UAFj3UpfDI39iklDr09Q","version":"1"}
{"action":{"identity":{"address":"N\u0000sourcecred\u0000core\u0000IDENTITY\u00009rk6vuxu0Ieg9L8amg8m7Q\u0000","aliases":[],"id":"9rk6vuxu0Ieg9L8amg8m7Q","name":"mercure-retrograde","subtype":"USER"},"type":"CREATE_IDENTITY"},"ledgerTimestamp":1643930401206,"uuid":"OZmpHzqkPkJnPV58B1FrUg","version":"1"}
{"action":{"alias":{"address":"N\u0000sourcecred\u0000discord\u0000MEMBER\u0000user\u0000845270253704446013\u0000","description":"discord/mercure-retrograde#2727"},"identityId":"9rk6vuxu0Ieg9L8amg8m7Q","type":"ADD_ALIAS"},"ledgerTimestamp":1643930401206,"uuid":"aHdaKbeh9Sw8a0NqPE08kg","version":"1"}
{"action":{"identity":{"address":"N\u0000sourcecred\u0000core\u0000IDENTITY\u0000Wxp6BNpr9EKWqrMEUERhZQ\u0000","aliases":[],"id":"Wxp6BNpr9EKWqrMEUERhZQ","name":"kato-discord","subtype":"USER"},"type":"CREATE_IDENTITY"},"ledgerTimestamp":1643930401206,"uuid":"Zr1kJCrQRdTmdwgaZtjDUw","version":"1"}
{"action":{"alias":{"address":"N\u0000sourcecred\u0000discord\u0000MEMBER\u0000user\u0000851828888765202443\u0000","description":"discord/kato#1085"},"identityId":"Wxp6BNpr9EKWqrMEUERhZQ","type":"ADD_ALIAS"},"ledgerTimestamp":1643930401206,"uuid":"V7mlh2go04VhJ3Gy7aFNeA","version":"1"}
{"action":{"identity":{"address":"N\u0000sourcecred\u0000core\u0000IDENTITY\u0000PxpQ7LvnCeyJt4tkdMzF6Q\u0000","aliases":[],"id":"PxpQ7LvnCeyJt4tkdMzF6Q","name":"queenofcups","subtype":"USER"},"type":"CREATE_IDENTITY"},"ledgerTimestamp":1643930401206,"uuid":"OeH3YphwfWBN9sj0vkIqGg","version":"1"}
{"action":{"alias":{"address":"N\u0000sourcecred\u0000discord\u0000MEMBER\u0000user\u0000853662166526984212\u0000","description":"discord/queenofcups#2474"},"identityId":"PxpQ7LvnCeyJt4tkdMzF6Q","type":"ADD_ALIAS"},"ledgerTimestamp":1643930401207,"uuid":"CjbgGXk78TRDtEaC7Krt6A","version":"1"}
{"action":{"identity":{"address":"N\u0000sourcecred\u0000core\u0000IDENTITY\u0000anacbjtZI6WCZ0i2VwANFw\u0000","aliases":[],"id":"anacbjtZI6WCZ0i2VwANFw","name":"CallyFromAuron","subtype":"USER"},"type":"CREATE_IDENTITY"},"ledgerTimestamp":1643930401207,"uuid":"N7uOSBMY0P3Oo4hvLw6yGA","version":"1"}
{"action":{"alias":{"address":"N\u0000sourcecred\u0000discord\u0000MEMBER\u0000user\u0000853681633570979841\u0000","description":"discord/CallyFromAuron#1714"},"identityId":"anacbjtZI6WCZ0i2VwANFw","type":"ADD_ALIAS"},"ledgerTimestamp":1643930401207,"uuid":"6t1ktkbY1hd5ZkezghgB7Q","version":"1"}
{"action":{"identity":{"address":"N\u0000sourcecred\u0000core\u0000IDENTITY\u0000ZOAP05JJVbvMgBu8A9vYpQ\u0000","aliases":[],"id":"ZOAP05JJVbvMgBu8A9vYpQ","name":"TCT","subtype":"USER"},"type":"CREATE_IDENTITY"},"ledgerTimestamp":1643930401208,"uuid":"jijRA1UaEcz7s3nho2y6Eg","version":"1"}
{"action":{"alias":{"address":"N\u0000sourcecred\u0000discord\u0000MEMBER\u0000user\u0000855233158751322122\u0000","description":"discord/TCT#8095"},"identityId":"ZOAP05JJVbvMgBu8A9vYpQ","type":"ADD_ALIAS"},"ledgerTimestamp":1643930401208,"uuid":"jxKSxeBiOTvQtwJlDKLWGw","version":"1"}
{"action":{"identity":{"address":"N\u0000sourcecred\u0000core\u0000IDENTITY\u00003PzeVkAGKy3SpMEwsqDLFw\u0000","aliases":[],"id":"3PzeVkAGKy3SpMEwsqDLFw","name":"AWG","subtype":"USER"},"type":"CREATE_IDENTITY"},"ledgerTimestamp":1643930401208,"uuid":"xQ4HGk8Q1dKZ9eYVblzSXg","version":"1"}
{"action":{"alias":{"address":"N\u0000sourcecred\u0000discord\u0000MEMBER\u0000user\u0000860097251535093780\u0000","description":"discord/AWG#6620"},"identityId":"3PzeVkAGKy3SpMEwsqDLFw","type":"ADD_ALIAS"},"ledgerTimestamp":1643930401209,"uuid":"86nPAOjVf2dDNuBqtXA4rg","version":"1"}
{"action":{"identity":{"address":"N\u0000sourcecred\u0000core\u0000IDENTITY\u000059c05QTO08dnx2604JFx9g\u0000","aliases":[],"id":"59c05QTO08dnx2604JFx9g","name":"SCBot","subtype":"BOT"},"type":"CREATE_IDENTITY"},"ledgerTimestamp":1643930401209,"uuid":"D5Drxw1X6e51sJaOX4pueA","version":"1"}
{"action":{"alias":{"address":"N\u0000sourcecred\u0000discord\u0000MEMBER\u0000bot\u0000864188114159009793\u0000","description":"discord/SCBot#5395"},"identityId":"59c05QTO08dnx2604JFx9g","type":"ADD_ALIAS"},"ledgerTimestamp":1643930401209,"uuid":"Pix0XkXj0yV5ErjU2LJd1w","version":"1"}
{"action":{"identity":{"address":"N\u0000sourcecred\u0000core\u0000IDENTITY\u0000QmdLd7H3feEs8691RZH0Xg\u0000","aliases":[],"id":"QmdLd7H3feEs8691RZH0Xg","name":"sarafanciulli","subtype":"USER"},"type":"CREATE_IDENTITY"},"ledgerTimestamp":1643930401209,"uuid":"ZDYSEPc4P7TKfW1ZKrZZhQ","version":"1"}
{"action":{"alias":{"address":"N\u0000sourcecred\u0000discord\u0000MEMBER\u0000user\u0000883468767756185660\u0000","description":"discord/sarafanciulli#8492"},"identityId":"QmdLd7H3feEs8691RZH0Xg","type":"ADD_ALIAS"},"ledgerTimestamp":1643930401209,"uuid":"DSpNV9ixHgswi5Idl4ATdg","version":"1"}
{"action":{"identity":{"address":"N\u0000sourcecred\u0000core\u0000IDENTITY\u0000GA6W7gJ5UWrdgOnYZn4VJw\u0000","aliases":[],"id":"GA6W7gJ5UWrdgOnYZn4VJw","name":"Jelani-Sasso","subtype":"USER"},"type":"CREATE_IDENTITY"},"ledgerTimestamp":1643930401210,"uuid":"VJ6rTLXtGRKUrT6w6QKMCA","version":"1"}
{"action":{"alias":{"address":"N\u0000sourcecred\u0000discord\u0000MEMBER\u0000user\u0000885426178637299753\u0000","description":"discord/Jelani-Sasso#0967"},"identityId":"GA6W7gJ5UWrdgOnYZn4VJw","type":"ADD_ALIAS"},"ledgerTimestamp":1643930401210,"uuid":"QQvnUJQUGDqpILp5vBoKeA","version":"1"}
{"action":{"identity":{"address":"N\u0000sourcecred\u0000core\u0000IDENTITY\u00000ezPPnuApOjcvmTy6yoxZA\u0000","aliases":[],"id":"0ezPPnuApOjcvmTy6yoxZA","name":"GptForMe","subtype":"USER"},"type":"CREATE_IDENTITY"},"ledgerTimestamp":1643930401210,"uuid":"3iPYZg7f08YD6vOI7vdZvg","version":"1"}
{"action":{"alias":{"address":"N\u0000sourcecred\u0000discord\u0000MEMBER\u0000user\u0000887797223092551760\u0000","description":"discord/GptForMe#2013"},"identityId":"0ezPPnuApOjcvmTy6yoxZA","type":"ADD_ALIAS"},"ledgerTimestamp":1643930401210,"uuid":"eYHWrZ2C1trN3mgDobnVvQ","version":"1"}
{"action":{"identity":{"address":"N\u0000sourcecred\u0000core\u0000IDENTITY\u00003EmND1Y2mXkOyogoBn7lOg\u0000","aliases":[],"id":"3EmND1Y2mXkOyogoBn7lOg","name":"Salvatore-Foglia","subtype":"USER"},"type":"CREATE_IDENTITY"},"ledgerTimestamp":1643930401211,"uuid":"ZwLQwP66KmEBzrE4aDwA8Q","version":"1"}
{"action":{"alias":{"address":"N\u0000sourcecred\u0000discord\u0000MEMBER\u0000user\u0000891725558126346330\u0000","description":"discord/Salvatore-Foglia#2182"},"identityId":"3EmND1Y2mXkOyogoBn7lOg","type":"ADD_ALIAS"},"ledgerTimestamp":1643930401211,"uuid":"qmqwO5t3bqU0zrFaMGaNdQ","version":"1"}
{"action":{"identity":{"address":"N\u0000sourcecred\u0000core\u0000IDENTITY\u0000Hw3aUGMkQ544Wew2fQdDeQ\u0000","aliases":[],"id":"Hw3aUGMkQ544Wew2fQdDeQ","name":"Kilgore-Trout","subtype":"USER"},"type":"CREATE_IDENTITY"},"ledgerTimestamp":1643930401212,"uuid":"8bT1hQKGyrjpebBqbAfEGA","version":"1"}
{"action":{"alias":{"address":"N\u0000sourcecred\u0000discord\u0000MEMBER\u0000user\u0000891812828787408978\u0000","description":"discord/Kilgore-Trout#9619"},"identityId":"Hw3aUGMkQ544Wew2fQdDeQ","type":"ADD_ALIAS"},"ledgerTimestamp":1643930401212,"uuid":"w1AP18IeqGID9DQ92favDw","version":"1"}
{"action":{"identity":{"address":"N\u0000sourcecred\u0000core\u0000IDENTITY\u0000LHPsWHL8gZQdiMAAHnIArA\u0000","aliases":[],"id":"LHPsWHL8gZQdiMAAHnIArA","name":"Silver-Collar-Syndicate","subtype":"USER"},"type":"CREATE_IDENTITY"},"ledgerTimestamp":1643930401212,"uuid":"SyOmF2JaosvKBLNk9rNkZw","version":"1"}
{"action":{"alias":{"address":"N\u0000sourcecred\u0000discord\u0000MEMBER\u0000user\u0000907853798570086471\u0000","description":"discord/Silver-Collar-Syndicate#3921"},"identityId":"LHPsWHL8gZQdiMAAHnIArA","type":"ADD_ALIAS"},"ledgerTimestamp":1643930401212,"uuid":"NyCbF3qW516Xn8eYABzL2A","version":"1"}
{"action":{"identity":{"address":"N\u0000sourcecred\u0000core\u0000IDENTITY\u0000GJAuE2cvKUL3FDJtOqIMug\u0000","aliases":[],"id":"GJAuE2cvKUL3FDJtOqIMug","name":"Maximilian","subtype":"USER"},"type":"CREATE_IDENTITY"},"ledgerTimestamp":1643930401212,"uuid":"4UWb7iWM1uKhg4heMOaKpA","version":"1"}
{"action":{"alias":{"address":"N\u0000sourcecred\u0000discord\u0000MEMBER\u0000user\u0000912359197469970485\u0000","description":"discord/Maximilian#3771"},"identityId":"GJAuE2cvKUL3FDJtOqIMug","type":"ADD_ALIAS"},"ledgerTimestamp":1643930401213,"uuid":"Xvba1ETnLyaCouDVm3hzyg","version":"1"}
{"action":{"identity":{"address":"N\u0000sourcecred\u0000core\u0000IDENTITY\u00005Bgo5NS2WhWjb4bX4JhwoQ\u0000","aliases":[],"id":"5Bgo5NS2WhWjb4bX4JhwoQ","name":"cangilz","subtype":"USER"},"type":"CREATE_IDENTITY"},"ledgerTimestamp":1643930401213,"uuid":"lZr7P2veHPYTliR6BhQOjw","version":"1"}
{"action":{"alias":{"address":"N\u0000sourcecred\u0000discord\u0000MEMBER\u0000user\u0000914185022574051369\u0000","description":"discord/cangilz#8671"},"identityId":"5Bgo5NS2WhWjb4bX4JhwoQ","type":"ADD_ALIAS"},"ledgerTimestamp":1643930401213,"uuid":"sMqkyA4MPzH4BNlgjfdxFg","version":"1"}
{"action":{"identity":{"address":"N\u0000sourcecred\u0000core\u0000IDENTITY\u0000AJHaTkBGeoea4f9dt6OEsQ\u0000","aliases":[],"id":"AJHaTkBGeoea4f9dt6OEsQ","name":"DanM3rcurius","subtype":"USER"},"type":"CREATE_IDENTITY"},"ledgerTimestamp":1643930405025,"uuid":"Hv8JSptoq5uXQkXxP9X9mQ","version":"1"}
{"action":{"alias":{"address":"N\u0000sourcecred\u0000github\u0000USERLIKE\u0000USER\u0000DanM3rcurius\u0000","description":"github/[@DanM3rcurius](https://github.com/DanM3rcurius)"},"identityId":"AJHaTkBGeoea4f9dt6OEsQ","type":"ADD_ALIAS"},"ledgerTimestamp":1643930405025,"uuid":"bo8qMRy54ZelGHwHLnBJpg","version":"1"}
{"action":{"identity":{"address":"N\u0000sourcecred\u0000core\u0000IDENTITY\u0000L3WWWR9ZYVUZrlY77AnTOQ\u0000","aliases":[],"id":"L3WWWR9ZYVUZrlY77AnTOQ","name":"tamagit80","subtype":"USER"},"type":"CREATE_IDENTITY"},"ledgerTimestamp":1643930405026,"uuid":"VuVmTvcw1h4w8uQL3Yx6sA","version":"1"}
{"action":{"alias":{"address":"N\u0000sourcecred\u0000github\u0000USERLIKE\u0000USER\u0000tamagit80\u0000","description":"github/[@tamagit80](https://github.com/tamagit80)"},"identityId":"L3WWWR9ZYVUZrlY77AnTOQ","type":"ADD_ALIAS"},"ledgerTimestamp":1643930405026,"uuid":"eBlL1JVz4Ir00Sr8u64O6Q","version":"1"}
{"action":{"identity":{"address":"N\u0000sourcecred\u0000core\u0000IDENTITY\u0000eNB2yW9OYoUp1c82DELQQQ\u0000","aliases":[],"id":"eNB2yW9OYoUp1c82DELQQQ","name":"wlstylr","subtype":"USER"},"type":"CREATE_IDENTITY"},"ledgerTimestamp":1643930405027,"uuid":"Cz05atg8xVpHKkgCXvKcXg","version":"1"}
{"action":{"alias":{"address":"N\u0000sourcecred\u0000github\u0000USERLIKE\u0000USER\u0000wlstylr\u0000","description":"github/[@wlstylr](https://github.com/wlstylr)"},"identityId":"eNB2yW9OYoUp1c82DELQQQ","type":"ADD_ALIAS"},"ledgerTimestamp":1643930405027,"uuid":"QFlwq6teIGIMs2OYWqK5fg","version":"1"}
{"action":{"identity":{"address":"N\u0000sourcecred\u0000core\u0000IDENTITY\u0000AFqqEoWzuJMjeOcgkKfDTQ\u0000","aliases":[],"id":"AFqqEoWzuJMjeOcgkKfDTQ","name":"evolayak","subtype":"USER"},"type":"CREATE_IDENTITY"},"ledgerTimestamp":1643930405027,"uuid":"z5eB6S9JQPxqcKT90qpcaQ","version":"1"}
{"action":{"alias":{"address":"N\u0000sourcecred\u0000github\u0000USERLIKE\u0000USER\u0000evolayak\u0000","description":"github/[@evolayak](https://github.com/evolayak)"},"identityId":"AFqqEoWzuJMjeOcgkKfDTQ","type":"ADD_ALIAS"},"ledgerTimestamp":1643930405029,"uuid":"UbTVW7pKTLpncqL3kbyMsQ","version":"1"}
{"action":{"identity":{"address":"N\u0000sourcecred\u0000core\u0000IDENTITY\u0000PsgLjA2xky3S05rNivpDHQ\u0000","aliases":[],"id":"PsgLjA2xky3S05rNivpDHQ","name":"Juliettervrd","subtype":"USER"},"type":"CREATE_IDENTITY"},"ledgerTimestamp":1643930405029,"uuid":"hnC7LCjIztzcoX4tPpbLyw","version":"1"}
{"action":{"alias":{"address":"N\u0000sourcecred\u0000github\u0000USERLIKE\u0000USER\u0000Juliettervrd\u0000","description":"github/[@Juliettervrd](https://github.com/Juliettervrd)"},"identityId":"PsgLjA2xky3S05rNivpDHQ","type":"ADD_ALIAS"},"ledgerTimestamp":1643930405029,"uuid":"QcxS2AXnnyOI73S4ODjyeg","version":"1"}
{"action":{"identity":{"address":"N\u0000sourcecred\u0000core\u0000IDENTITY\u0000EMR7SdBUZtWmJTMPwOcypA\u0000","aliases":[],"id":"EMR7SdBUZtWmJTMPwOcypA","name":"stephen-rowan","subtype":"USER"},"type":"CREATE_IDENTITY"},"ledgerTimestamp":1643930405031,"uuid":"aAtrk9AK6mMaNvxwtK44eg","version":"1"}
{"action":{"alias":{"address":"N\u0000sourcecred\u0000github\u0000USERLIKE\u0000USER\u0000stephen-rowan\u0000","description":"github/[@stephen-rowan](https://github.com/stephen-rowan)"},"identityId":"EMR7SdBUZtWmJTMPwOcypA","type":"ADD_ALIAS"},"ledgerTimestamp":1643930405031,"uuid":"iyLUGySZwUPQa3ES8QopfA","version":"1"}
{"action":{"identity":{"address":"N\u0000sourcecred\u0000core\u0000IDENTITY\u0000cXFDz1ApPSjlbrJl5093dw\u0000","aliases":[],"id":"cXFDz1ApPSjlbrJl5093dw","name":"jkochevar","subtype":"USER"},"type":"CREATE_IDENTITY"},"ledgerTimestamp":1643930405031,"uuid":"sxZZ0MRFVLpXhwulfBzKEA","version":"1"}
{"action":{"alias":{"address":"N\u0000sourcecred\u0000github\u0000USERLIKE\u0000USER\u0000jkochevar\u0000","description":"github/[@jkochevar](https://github.com/jkochevar)"},"identityId":"cXFDz1ApPSjlbrJl5093dw","type":"ADD_ALIAS"},"ledgerTimestamp":1643930405031,"uuid":"2xuwrMAxU4MvhAfjYHz8rQ","version":"1"}
{"action":{"identity":{"address":"N\u0000sourcecred\u0000core\u0000IDENTITY\u0000BwVnN8ncJ9yg3qSZWlexFQ\u0000","aliases":[],"id":"BwVnN8ncJ9yg3qSZWlexFQ","name":"TheHiddenOrder","subtype":"USER"},"type":"CREATE_IDENTITY"},"ledgerTimestamp":1643930405031,"uuid":"GRwnA81UmagQAuNPzWM2gQ","version":"1"}
{"action":{"alias":{"address":"N\u0000sourcecred\u0000github\u0000USERLIKE\u0000USER\u0000TheHiddenOrder\u0000","description":"github/[@TheHiddenOrder](https://github.com/TheHiddenOrder)"},"identityId":"BwVnN8ncJ9yg3qSZWlexFQ","type":"ADD_ALIAS"},"ledgerTimestamp":1643930405032,"uuid":"aVNjer9vGFgUWZMPkt1w8g","version":"1"}
{"action":{"identity":{"address":"N\u0000sourcecred\u0000core\u0000IDENTITY\u0000mBHRgFLaIboo6QI3SPLxLw\u0000","aliases":[],"id":"mBHRgFLaIboo6QI3SPLxLw","name":"Pythag0rean","subtype":"USER"},"type":"CREATE_IDENTITY"},"ledgerTimestamp":1643930405032,"uuid":"WU8bRwb1exJOk5K8cn3O6A","version":"1"}
{"action":{"alias":{"address":"N\u0000sourcecred\u0000github\u0000USERLIKE\u0000USER\u0000Pythag0rean\u0000","description":"github/[@Pythag0rean](https://github.com/Pythag0rean)"},"identityId":"mBHRgFLaIboo6QI3SPLxLw","type":"ADD_ALIAS"},"ledgerTimestamp":1643930405032,"uuid":"xe3ba4wnMH1G5gzDxHjOnQ","version":"1"}
{"action":{"identity":{"address":"N\u0000sourcecred\u0000core\u0000IDENTITY\u0000JjN3JZaEGLAtQB1QHG5YsA\u0000","aliases":[],"id":"JjN3JZaEGLAtQB1QHG5YsA","name":"mbaldwin2015","subtype":"USER"},"type":"CREATE_IDENTITY"},"ledgerTimestamp":1643930405032,"uuid":"lj6N76tKeImrIM2pcKvTEw","version":"1"}
{"action":{"alias":{"address":"N\u0000sourcecred\u0000github\u0000USERLIKE\u0000USER\u0000mbaldwin2015\u0000","description":"github/[@mbaldwin2015](https://github.com/mbaldwin2015)"},"identityId":"JjN3JZaEGLAtQB1QHG5YsA","type":"ADD_ALIAS"},"ledgerTimestamp":1643930405032,"uuid":"XjxIPe4YzSK13LSVG83E5A","version":"1"}
{"action":{"identity":{"address":"N\u0000sourcecred\u0000core\u0000IDENTITY\u0000KVYGj9S2SV0U4nKEdHkBVA\u0000","aliases":[],"id":"KVYGj9S2SV0U4nKEdHkBVA","name":"sarafanciulli-github","subtype":"USER"},"type":"CREATE_IDENTITY"},"ledgerTimestamp":1643930405033,"uuid":"bQK6vh6I8QMpL3wK2YeyVA","version":"1"}
{"action":{"alias":{"address":"N\u0000sourcecred\u0000github\u0000USERLIKE\u0000USER\u0000sarafanciulli\u0000","description":"github/[@sarafanciulli](https://github.com/sarafanciulli)"},"identityId":"KVYGj9S2SV0U4nKEdHkBVA","type":"ADD_ALIAS"},"ledgerTimestamp":1643930405033,"uuid":"KIqwf1CY9F7sYQXTk5MU4w","version":"1"}
{"action":{"identity":{"address":"N\u0000sourcecred\u0000core\u0000IDENTITY\u00005PYbYFoi3SNhwrnNphYt1g\u0000","aliases":[],"id":"5PYbYFoi3SNhwrnNphYt1g","name":"SourceCred","subtype":"PROJECT"},"type":"CREATE_IDENTITY"},"ledgerTimestamp":1643930405710,"uuid":"Gki18MfL3Ua9E2HBjs3tzg","version":"1"}
{"action":{"identityId":"5PYbYFoi3SNhwrnNphYt1g","type":"TOGGLE_ACTIVATION"},"ledgerTimestamp":1643930405710,"uuid":"AQYA2r2kkCE8GXLe9xLJRg","version":"1"}
